<?xml version="1.0" encoding="utf-8"?>
<S>
   <aparc_DK40>
      <ids>[1639705;1639705;2647065;2647065;10511485;10511485;6500;6500;3294840;3294840;6558940;6558940;660700;660700;9231540;9231540;14433500;14433500;7874740;7874740;9180300;9180300;9182740;9182740;3296035;3296035;9211105;9211105;4924360;4924360;3302560;3302560;3988500;3988500;3988540;3988540;9221340;9221340;3302420;3302420;1326300;1326300;3957880;3957880;1316060;1316060;14464220;14464220;14423100;14423100;11832480;11832480;9180240;9180240;8204875;8204875;10542100;10542100;9221140;9221140;14474380;14474380;1351760;1351760;6553700;6553700;11146310;11146310;13145750;13145750;2146559;2146559]</ids>
      <names>
         <item>lunknown</item>
         <item>runknown</item>
         <item>lbankssts</item>
         <item>rbankssts</item>
         <item>lcaudalanteriorcingulate</item>
         <item>rcaudalanteriorcingulate</item>
         <item>lcaudalmiddlefrontal</item>
         <item>rcaudalmiddlefrontal</item>
         <item>lcorpuscallosum</item>
         <item>rcorpuscallosum</item>
         <item>lcuneus</item>
         <item>rcuneus</item>
         <item>lentorhinal</item>
         <item>rentorhinal</item>
         <item>lfusiform</item>
         <item>rfusiform</item>
         <item>linferiorparietal</item>
         <item>rinferiorparietal</item>
         <item>linferiortemporal</item>
         <item>rinferiortemporal</item>
         <item>listhmuscingulate</item>
         <item>risthmuscingulate</item>
         <item>llateraloccipital</item>
         <item>rlateraloccipital</item>
         <item>llateralorbitofrontal</item>
         <item>rlateralorbitofrontal</item>
         <item>llingual</item>
         <item>rlingual</item>
         <item>lmedialorbitofrontal</item>
         <item>rmedialorbitofrontal</item>
         <item>lmiddletemporal</item>
         <item>rmiddletemporal</item>
         <item>lparahippocampal</item>
         <item>rparahippocampal</item>
         <item>lparacentral</item>
         <item>rparacentral</item>
         <item>lparsopercularis</item>
         <item>rparsopercularis</item>
         <item>lparsorbitalis</item>
         <item>rparsorbitalis</item>
         <item>lparstriangularis</item>
         <item>rparstriangularis</item>
         <item>lpericalcarine</item>
         <item>rpericalcarine</item>
         <item>lpostcentral</item>
         <item>rpostcentral</item>
         <item>lposteriorcingulate</item>
         <item>rposteriorcingulate</item>
         <item>lprecentral</item>
         <item>rprecentral</item>
         <item>lprecuneus</item>
         <item>rprecuneus</item>
         <item>lrostralanteriorcingulate</item>
         <item>rrostralanteriorcingulate</item>
         <item>lrostralmiddlefrontal</item>
         <item>rrostralmiddlefrontal</item>
         <item>lsuperiorfrontal</item>
         <item>rsuperiorfrontal</item>
         <item>lsuperiorparietal</item>
         <item>rsuperiorparietal</item>
         <item>lsuperiortemporal</item>
         <item>rsuperiortemporal</item>
         <item>lsupramarginal</item>
         <item>rsupramarginal</item>
         <item>lfrontalpole</item>
         <item>rfrontalpole</item>
         <item>ltemporalpole</item>
         <item>rtemporalpole</item>
         <item>ltransversetemporal</item>
         <item>rtransversetemporal</item>
         <item>linsula</item>
         <item>rinsula</item>
      </names>
      <comments>
         <item>cat_surf_surf2roi</item>
      </comments>
      <version>2577</version>
      <data>
         <thickness>[2.44053614139557;NaN;2.29281251978305;2.87702673000499;2.92157858374054;2.07357434731959;2.87364510454764;2.74929563434177;NaN;NaN;2.74743529645943;2.05961774877285;3.03998440190365;2.58975112557147;2.53243363958119;2.63098570352152;2.43237749386161;2.67715984074081;2.1512202363727;2.81365152448061;2.92272308069649;2.0381556659238;2.23476867889569;2.30190684825167;2.86045610696903;2.79319458607144;2.88798725758098;2.13203777497587;3.07430986027155;2.43057937236481;2.09927042630591;2.90613146105938;2.92698937648009;2.18064503195502;2.2722976901854;2.12881859277378;2.64662765279417;2.77602308988571;2.66276702708779;2.89844284677606;2.54057697580357;2.60713286469964;2.73222443062391;1.614555096829;1.92804651105588;2.186671397375;2.84162726970954;2.37889394590117;2.46336530502504;2.230818480256;2.61613944645912;2.52114888144885;3.00682307570069;2.42061576595996;2.67966241032054;2.59368926418579;2.58508843831;2.85002285538147;2.5158031163502;2.49177212759231;1.72274699757572;2.92524190588128;2.41939037766568;2.70597027240355;2.72430456035277;2.61479480576709;3.56453931601596;3.849991960508;0.862206216817512;2.74809978743979;1.8713298005113;3.18648422837023]</thickness>
         <gyrification>[19.2406921386719;NaN;28.5082107736064;28.8845024083916;25.5506624525997;33.0213409226332;27.9346240119454;29.5547512571131;NaN;NaN;27.8319365656449;29.3240526199923;27.9300328430377;24.9330148044024;27.4238076002152;27.8621674551777;29.574327905059;29.4874802319754;28.5764244068249;27.0610133669046;26.9149821456456;28.388750353151;30.940182956152;30.7188415420989;27.8408774958982;28.6735460526581;27.2677134562049;29.5800308508939;29.6492157604305;29.7630388265165;27.07385918731;26.2007865041571;23.0558033618626;23.7714626659071;28.0694283603102;28.5881743987464;31.9379427922234;29.1930342410182;30.4718563716282;29.4676623369624;31.043368847489;30.9648803222079;30.2577937217936;27.9993738570974;28.9389465369025;25.7452522569998;28.9646856033649;30.4370515876081;28.7679687658058;28.8562512592532;29.2472257591625;30.6279817284163;28.747193820918;34.0166542623068;30.2535579922481;29.943120051073;28.9421602306484;29.3596260300147;27.9065664584457;28.7949599532949;25.1366477216713;26.7458426857592;30.6857990202793;29.3713331223412;35.5964978687903;32.1572143075266;27.4525867324052;24.4187689603761;16.9630790508835;26.9097393142124;23.3876131625722;27.0262912210641]</gyrification>
      </data>
   </aparc_DK40>
   <aparc_a2009s>
      <ids>[0;0;3988503;3988503;11811863;11811863;3957823;3957823;14423103;14423103;16384013;16384013;15386;15386;4930586;4930586;9845786;9845786;16399385;16399385;1644860;1644860;1316020;1316020;6558940;6558940;3947660;3947660;9231540;9231540;11822220;11822220;9180340;9180340;657943;657943;9211105;9211105;11812020;11812020;3988500;3988500;9180220;9180220;9221340;9221340;1336385;1336385;1326300;1326300;14433300;14433300;3957860;3957860;14464220;14464220;9221140;9221140;11832380;11832380;9180185;9180185;6568980;6568980;1367100;1367100;14433340;14433340;14433500;14433500;3988545;3988545;1346585;1346585;6610140;6610140;3947700;3947700;14423101;14423101;3937341;3937341;6569021;6569021;1644825;1644825;3937420;3937420;1357020;1357020;11842623;11842623;660701;660701;6558941;6558941;9190621;9190621;14423261;14423261;14474301;14474301;13158500;13158500;13158410;13158410;1367261;1367261;6558861;6558861;6609981;6609981;1326221;1326221;14423183;14423183;14433381;14433381;9180181;9180181;11801661;11801661;1346781;1346781;14443661;14443661;1336541;1336541;1362101;1362101;1315941;1315941;11822181;11822181;1367221;1367221;13143061;13143061;15733781;15733781;13112341;13112341;3937301;3937301;3947621;3947621;11842581;11842581;3988703;3988703;3947741;3947741]</ids>
      <names>
         <item>lUnknown</item>
         <item>rUnknown</item>
         <item>lG_and_S_frontomargin</item>
         <item>rG_and_S_frontomargin</item>
         <item>lG_and_S_occipital_inf</item>
         <item>rG_and_S_occipital_inf</item>
         <item>lG_and_S_paracentral</item>
         <item>rG_and_S_paracentral</item>
         <item>lG_and_S_subcentral</item>
         <item>rG_and_S_subcentral</item>
         <item>lG_and_S_transv_frontopol</item>
         <item>rG_and_S_transv_frontopol</item>
         <item>lG_and_S_cingul-Ant</item>
         <item>rG_and_S_cingul-Ant</item>
         <item>lG_and_S_cingul-Mid-Ant</item>
         <item>rG_and_S_cingul-Mid-Ant</item>
         <item>lG_and_S_cingul-Mid-Post</item>
         <item>rG_and_S_cingul-Mid-Post</item>
         <item>lG_cingul-Post-dorsal</item>
         <item>rG_cingul-Post-dorsal</item>
         <item>lG_cingul-Post-ventral</item>
         <item>rG_cingul-Post-ventral</item>
         <item>lG_cuneus</item>
         <item>rG_cuneus</item>
         <item>lG_front_inf-Opercular</item>
         <item>rG_front_inf-Opercular</item>
         <item>lG_front_inf-Orbital</item>
         <item>rG_front_inf-Orbital</item>
         <item>lG_front_inf-Triangul</item>
         <item>rG_front_inf-Triangul</item>
         <item>lG_front_middle</item>
         <item>rG_front_middle</item>
         <item>lG_front_sup</item>
         <item>rG_front_sup</item>
         <item>lG_Ins_lg_and_S_cent_ins</item>
         <item>rG_Ins_lg_and_S_cent_ins</item>
         <item>lG_insular_short</item>
         <item>rG_insular_short</item>
         <item>lG_occipital_middle</item>
         <item>rG_occipital_middle</item>
         <item>lG_occipital_sup</item>
         <item>rG_occipital_sup</item>
         <item>lG_oc-temp_lat-fusifor</item>
         <item>rG_oc-temp_lat-fusifor</item>
         <item>lG_oc-temp_med-Lingual</item>
         <item>rG_oc-temp_med-Lingual</item>
         <item>lG_oc-temp_med-Parahip</item>
         <item>rG_oc-temp_med-Parahip</item>
         <item>lG_orbital</item>
         <item>rG_orbital</item>
         <item>lG_pariet_inf-Angular</item>
         <item>rG_pariet_inf-Angular</item>
         <item>lG_pariet_inf-Supramar</item>
         <item>rG_pariet_inf-Supramar</item>
         <item>lG_parietal_sup</item>
         <item>rG_parietal_sup</item>
         <item>lG_postcentral</item>
         <item>rG_postcentral</item>
         <item>lG_precentral</item>
         <item>rG_precentral</item>
         <item>lG_precuneus</item>
         <item>rG_precuneus</item>
         <item>lG_rectus</item>
         <item>rG_rectus</item>
         <item>lG_subcallosal</item>
         <item>rG_subcallosal</item>
         <item>lG_temp_sup-G_T_transv</item>
         <item>rG_temp_sup-G_T_transv</item>
         <item>lG_temp_sup-Lateral</item>
         <item>rG_temp_sup-Lateral</item>
         <item>lG_temp_sup-Plan_polar</item>
         <item>rG_temp_sup-Plan_polar</item>
         <item>lG_temp_sup-Plan_tempo</item>
         <item>rG_temp_sup-Plan_tempo</item>
         <item>lG_temporal_inf</item>
         <item>rG_temporal_inf</item>
         <item>lG_temporal_middle</item>
         <item>rG_temporal_middle</item>
         <item>lLat_Fis-ant-Horizont</item>
         <item>rLat_Fis-ant-Horizont</item>
         <item>lLat_Fis-ant-Vertical</item>
         <item>rLat_Fis-ant-Vertical</item>
         <item>lLat_Fis-post</item>
         <item>rLat_Fis-post</item>
         <item>lMedial_wall</item>
         <item>rMedial_wall</item>
         <item>lPole_occipital</item>
         <item>rPole_occipital</item>
         <item>lPole_temporal</item>
         <item>rPole_temporal</item>
         <item>lS_calcarine</item>
         <item>rS_calcarine</item>
         <item>lS_central</item>
         <item>rS_central</item>
         <item>lS_cingul-Marginalis</item>
         <item>rS_cingul-Marginalis</item>
         <item>lS_circular_insula_ant</item>
         <item>rS_circular_insula_ant</item>
         <item>lS_circular_insula_inf</item>
         <item>rS_circular_insula_inf</item>
         <item>lS_circular_insula_sup</item>
         <item>rS_circular_insula_sup</item>
         <item>lS_collat_transv_ant</item>
         <item>rS_collat_transv_ant</item>
         <item>lS_collat_transv_post</item>
         <item>rS_collat_transv_post</item>
         <item>lS_front_inf</item>
         <item>rS_front_inf</item>
         <item>lS_front_middle</item>
         <item>rS_front_middle</item>
         <item>lS_front_sup</item>
         <item>rS_front_sup</item>
         <item>lS_interm_prim-Jensen</item>
         <item>rS_interm_prim-Jensen</item>
         <item>lS_intrapariet_and_P_trans</item>
         <item>rS_intrapariet_and_P_trans</item>
         <item>lS_oc_middle_and_Lunatus</item>
         <item>rS_oc_middle_and_Lunatus</item>
         <item>lS_oc_sup_and_transversal</item>
         <item>rS_oc_sup_and_transversal</item>
         <item>lS_occipital_ant</item>
         <item>rS_occipital_ant</item>
         <item>lS_oc-temp_lat</item>
         <item>rS_oc-temp_lat</item>
         <item>lS_oc-temp_med_and_Lingual</item>
         <item>rS_oc-temp_med_and_Lingual</item>
         <item>lS_orbital_lateral</item>
         <item>rS_orbital_lateral</item>
         <item>lS_orbital_med-olfact</item>
         <item>rS_orbital_med-olfact</item>
         <item>lS_orbital-H_Shaped</item>
         <item>rS_orbital-H_Shaped</item>
         <item>lS_parieto_occipital</item>
         <item>rS_parieto_occipital</item>
         <item>lS_pericallosal</item>
         <item>rS_pericallosal</item>
         <item>lS_postcentral</item>
         <item>rS_postcentral</item>
         <item>lS_precentral-inf-part</item>
         <item>rS_precentral-inf-part</item>
         <item>lS_precentral-sup-part</item>
         <item>rS_precentral-sup-part</item>
         <item>lS_suborbital</item>
         <item>rS_suborbital</item>
         <item>lS_subparietal</item>
         <item>rS_subparietal</item>
         <item>lS_temporal_inf</item>
         <item>rS_temporal_inf</item>
         <item>lS_temporal_sup</item>
         <item>rS_temporal_sup</item>
         <item>lS_temporal_transverse</item>
         <item>rS_temporal_transverse</item>
      </names>
      <comments>
         <item>cat_surf_surf2roi</item>
      </comments>
      <version>2577</version>
      <data>
         <thickness>[2.9849307171047;1.80469159755377;2.80080781525297;2.51831609110037;2.13624391288802;2.48216634752088;2.03535236418247;1.83599210032065;2.47308008143579;2.83545899955379;2.53264795022718;2.61123055025052;2.82655928339183;2.56353461380651;2.84535056769878;2.65800636526558;2.86553399920563;2.63741978409947;2.78052075595369;2.75323390250345;2.8759047132272;2.07888301045864;2.71135126927516;1.90481425401067;2.56353999873002;2.90889127537304;2.40241802988726;2.62731922293703;2.6431666297106;2.68810354483117;2.66829257017582;2.73477667577471;2.47576755822088;2.85902279418387;1.69900781699058;3.13804231549773;1.93309787077047;3.57199373489423;2.16917527662333;2.63731404137964;2.74599033528632;2.52056438957837;2.69673029056092;2.70698116574034;2.85354370975802;2.06265979377425;3.01730558448872;2.48448405317522;2.93569671199435;2.91568309392116;2.58514914411375;2.75899477090154;2.55100732867239;2.90135285671028;2.41777330704775;2.65874547509552;1.65977961808469;2.12033433485669;2.60031170123502;2.27332865410923;2.55158097006507;2.60070266125001;3.13069760162032;2.44870951957201;3.19241060217222;2.75032615093958;0.858965849992949;2.7331693818796;1.86269475958556;3.09659523560755;3.33817061084978;3.46163553714752;1.70063526360664;2.86822743075235;2.04104164670506;2.91428898071015;2.06647582198915;2.95081014267609;2.63632524109142;2.64973205979131;2.44227852143588;2.64282337285705;1.11576625964686;2.70895561008226;NaN;NaN;2.47104076315195;1.97162647736051;2.82900587120808;3.25679186612728;2.83060433791174;2.00574636508913;2.1259056258648;1.67427052667594;2.54524572348843;2.48031233926953;2.5631461072424;3.1578083980199;1.75329876490545;3.09922441066937;1.96677809444611;2.88423170005987;2.54565622783764;2.61993341856681;2.67684119146306;2.36652414071851;2.92546198701464;2.50309534578368;2.61239804552738;2.58949751405421;2.71367672173271;2.71728675774261;2.447939306018;2.5228459420543;2.63055433067612;2.42422461364769;2.4184202923509;2.44526529413404;2.42237496961055;2.28577239905935;1.60625736797934;2.63195742249076;2.44295430077092;2.54918967374687;2.67931889667284;2.25844964492545;2.41186398100317;2.34351635298559;3.33634309409019;2.29724496070268;2.85312220249055;2.66878290391564;2.76342773518047;2.35311303403521;2.90137352773049;1.37425455010255;2.29773899027544;2.25903858867598;3.04013896356042;2.64271208501845;2.65149092248047;2.59023388822873;2.95034678268304;2.69717911704859;2.83959478328472;2.57775009660858;2.02777050321538;2.70309515703808;2.17841453289808;2.74840345479549;0.822809658151992;2.64592949761028]</thickness>
         <gyrification>[26.788414103085;23.3598738866878;28.3272315900725;32.2886290899345;31.6089572099941;28.9180799566882;26.3457517829579;28.6183472901688;31.7232878856564;26.5174544808344;34.352192344848;30.9446579023313;29.7964013158753;32.1216187339983;26.9566619553369;31.926925444744;27.814434242968;30.5106074009217;30.9269706855489;29.4566570614684;25.709916301874;24.5446394581299;29.3639616145954;29.2311830172453;31.456434110668;29.4668492860332;30.2647497332912;33.0254659222232;31.5126086092707;28.9136709482642;29.1032947947255;29.6093521992738;28.3853240707729;28.8177161179758;26.4789257806051;29.0046357309727;24.5735263876069;27.9975979182323;30.449659117525;31.0937385693499;30.7134733954629;28.8207853240943;27.769018507228;26.5843022135478;28.1975995463034;30.501668603043;24.5529850423336;23.6587700726521;26.8345284977603;26.8434551205746;29.2847307243863;29.8787572092891;30.9502363219155;27.4882323783471;27.1002537767752;29.0068510042535;28.525227525629;27.149103260253;29.3407677006057;28.1905583352205;28.5841767765708;30.1917147516566;27.7232614961782;28.2149360658273;27.6955561975638;23.3578775537995;17.8114577561783;25.3749473253315;26.6737673682557;27.3892942496978;29.7079295983186;25.737448949496;27.1788244473721;25.0290226982998;29.2020523429669;26.0263634336399;27.7260117861512;26.9694663245168;29.4385801623849;30.565130622447;33.3623187715007;31.9302772166365;19.5932345555281;29.6952435558293;NaN;NaN;30.3943735793733;31.1203627491167;22.6397741880136;27.2608025391372;29.1476835861392;28.4958102236773;29.3329766863577;28.9635454409804;28.6872965853661;30.4102690154341;25.5110739669328;27.5863093739562;24.7387171056858;25.2766435366507;27.1920461871022;28.9740184483546;28.2133034688302;27.9816844356194;27.7319607099881;28.9750512041697;30.665359379177;29.4380835746236;29.5289729778157;30.0895612379034;29.3313124375704;28.1510971413476;34.1948890587379;34.616068595557;29.3209053838461;27.7729914722695;29.0156451680557;31.7450964317738;30.2870314291956;29.2565096483218;30.1452134250137;30.6047861807074;30.4981643151546;30.9835969132804;27.3373187288148;27.1336001285628;31.7456347553918;32.0996356790974;30.0363978202616;27.2777398738199;31.9174159588157;32.4253010861245;29.8813079112285;29.230254685639;26.8539099567815;31.1390076660433;28.4562542053831;27.6392173098739;26.6292810531324;29.8650481744316;28.8297792447091;27.8918254353106;31.2283122713032;30.6060403852485;29.0218578725286;31.3429250479799;27.7223618309526;28.8333276553136;28.8134593308524;27.7209642297806;14.4961576962196;25.1659755764516]</gyrification>
      </data>
   </aparc_a2009s>
</S>